superduper_snowflake/__init__.py
superduper_snowflake/connect.py
superduper_snowflake/data_backend.py
superduper_snowflake/database_listener.py
superduper_snowflake/query.py
superduper_snowflake/schema.py
superduper_snowflake/secrets.py
superduper_snowflake/vector_search.py
superduper_snowflake-0.10.0.dist-info/licenses/LICENSE
superduper_snowflake-0.10.0.dist-info/METADATA
superduper_snowflake-0.10.0.dist-info/WHEEL
superduper_snowflake-0.10.0.dist-info/top_level.txt
superduper_snowflake-0.10.0.dist-info/RECORD
