Metadata-Version: 2.4
Name: superduper_snowflake
Version: 0.10.0
Summary: Superduper snowflake is a plugin for snowflake-framework that allows you to use Superduper as a backend for your snowflake queries.
Maintainer-email: "superduper.io, Inc." <opensource@superduper.io>
License: 
Project-URL: homepage, https://superduper.io
Project-URL: documentation, https://docs.superduper.io/docs/intro
Project-URL: source, https://github.com/superduper-io/superduper
Keywords: databases,mongodb,data-science,machine-learning,mlops,vector-database,ai
Requires-Python: >=3.10
License-File: LICENSE
Requires-Dist: snowflake
Requires-Dist: snowflake-snowpark-python[localtest]
Requires-Dist: snowflake-connector-python==3.15.0
Requires-Dist: snowflake-sqlalchemy
Requires-Dist: watchdog>=6.0.0
Requires-Dist: ibis-framework[snowflake]
Provides-Extra: test
Dynamic: license-file
